{"info":{"file":"components/templates/templates.js","fileShort":"components/templates/templates.js","fileSafe":"components_templates_templates_js","link":"files/components_templates_templates_js/index.html"},"complexity":{"aggregate":{"line":31,"complexity":{"sloc":{"physical":324,"logical":127},"cyclomatic":29,"halstead":{"operators":{"distinct":23,"total":297,"identifiers":["__stripped__"]},"operands":{"distinct":89,"total":340,"identifiers":["__stripped__"]},"length":637,"vocabulary":112,"difficulty":43.93258426966292,"volume":4336.285085350693,"effort":190504.20992945178,"bugs":1.4454283617835644,"time":10583.567218302876}}},"functions":[{"name":"<anonymous>","line":34,"complexity":{"sloc":{"physical":320,"logical":10},"cyclomatic":1,"halstead":{"operators":{"distinct":5,"total":22,"identifiers":["__stripped__"]},"operands":{"distinct":13,"total":21,"identifiers":["__stripped__"]},"length":43,"vocabulary":18,"difficulty":4.038461538461538,"volume":179.30677506201943,"effort":724.12351467354,"bugs":0.059768925020673144,"time":40.22908414853}}},{"name":"getTarget","line":46,"complexity":{"sloc":{"physical":8,"logical":4},"cyclomatic":2,"halstead":{"operators":{"distinct":7,"total":9,"identifiers":["__stripped__"]},"operands":{"distinct":5,"total":10,"identifiers":["__stripped__"]},"length":19,"vocabulary":12,"difficulty":7,"volume":68.11428751370197,"effort":476.80001259591376,"bugs":0.022704762504567322,"time":26.488889588661877}}},{"name":"getTemplate","line":65,"complexity":{"sloc":{"physical":49,"logical":30},"cyclomatic":10,"halstead":{"operators":{"distinct":15,"total":64,"identifiers":["__stripped__"]},"operands":{"distinct":21,"total":73,"identifiers":["__stripped__"]},"length":137,"vocabulary":36,"difficulty":26.071428571428573,"volume":708.2797251975968,"effort":18465.864264080203,"bugs":0.23609324173253227,"time":1025.8813480044557}}},{"name":"templateReplace","line":123,"complexity":{"sloc":{"physical":9,"logical":1},"cyclomatic":1,"halstead":{"operators":{"distinct":2,"total":2,"identifiers":["__stripped__"]},"operands":{"distinct":2,"total":2,"identifiers":["__stripped__"]},"length":4,"vocabulary":4,"difficulty":1,"volume":8,"effort":8,"bugs":0.0026666666666666666,"time":0.4444444444444444}}},{"name":"<anonymous>","line":124,"complexity":{"sloc":{"physical":7,"logical":4},"cyclomatic":2,"halstead":{"operators":{"distinct":7,"total":8,"identifiers":["__stripped__"]},"operands":{"distinct":6,"total":11,"identifiers":["__stripped__"]},"length":19,"vocabulary":13,"difficulty":6.416666666666666,"volume":70.30835464468075,"effort":451.1452756367014,"bugs":0.02343611821489358,"time":25.063626424261187}}},{"name":"get","line":144,"complexity":{"sloc":{"physical":29,"logical":3},"cyclomatic":1,"halstead":{"operators":{"distinct":6,"total":7,"identifiers":["__stripped__"]},"operands":{"distinct":6,"total":10,"identifiers":["__stripped__"]},"length":17,"vocabulary":12,"difficulty":5,"volume":60.94436251225966,"effort":304.7218125612983,"bugs":0.020314787504086555,"time":16.928989586738794}}},{"name":"doGet","line":146,"complexity":{"sloc":{"physical":23,"logical":14},"cyclomatic":5,"halstead":{"operators":{"distinct":11,"total":34,"identifiers":["__stripped__"]},"operands":{"distinct":11,"total":33,"identifiers":["__stripped__"]},"length":67,"vocabulary":22,"difficulty":16.5,"volume":298.78191844869895,"effort":4929.901654403533,"bugs":0.09959397281623299,"time":273.8834252446407}}},{"name":"add","line":193,"complexity":{"sloc":{"physical":46,"logical":11},"cyclomatic":2,"halstead":{"operators":{"distinct":9,"total":21,"identifiers":["__stripped__"]},"operands":{"distinct":17,"total":25,"identifiers":["__stripped__"]},"length":46,"vocabulary":26,"difficulty":6.61764705882353,"volume":216.22022703449025,"effort":1430.8691494929503,"bugs":0.07207340901149675,"time":79.49273052738613}}},{"name":"<anonymous>","line":208,"complexity":{"sloc":{"physical":28,"logical":16},"cyclomatic":7,"halstead":{"operators":{"distinct":8,"total":33,"identifiers":["__stripped__"]},"operands":{"distinct":20,"total":41,"identifiers":["__stripped__"]},"length":74,"vocabulary":28,"difficulty":8.2,"volume":355.74426423226265,"effort":2917.1029667045536,"bugs":0.11858142141075421,"time":162.06127592803077}}},{"name":"Templates.append","line":258,"complexity":{"sloc":{"physical":5,"logical":2},"cyclomatic":1,"halstead":{"operators":{"distinct":5,"total":6,"identifiers":["__stripped__"]},"operands":{"distinct":7,"total":10,"identifiers":["__stripped__"]},"length":16,"vocabulary":12,"difficulty":3.5714285714285716,"volume":57.359400011538504,"effort":204.85500004120897,"bugs":0.01911980000384617,"time":11.38083333562272}}},{"name":"Templates.prepend","line":281,"complexity":{"sloc":{"physical":5,"logical":2},"cyclomatic":1,"halstead":{"operators":{"distinct":5,"total":6,"identifiers":["__stripped__"]},"operands":{"distinct":7,"total":10,"identifiers":["__stripped__"]},"length":16,"vocabulary":12,"difficulty":3.5714285714285716,"volume":57.359400011538504,"effort":204.85500004120897,"bugs":0.01911980000384617,"time":11.38083333562272}}},{"name":"Templates.render","line":298,"complexity":{"sloc":{"physical":34,"logical":19},"cyclomatic":4,"halstead":{"operators":{"distinct":10,"total":54,"identifiers":["__stripped__"]},"operands":{"distinct":28,"total":63,"identifiers":["__stripped__"]},"length":117,"vocabulary":38,"difficulty":11.25,"volume":614.0075190728994,"effort":6907.584589570119,"bugs":0.2046691730242998,"time":383.75469942056213}}},{"name":"Templates.clear","line":340,"complexity":{"sloc":{"physical":13,"logical":7},"cyclomatic":2,"halstead":{"operators":{"distinct":7,"total":21,"identifiers":["__stripped__"]},"operands":{"distinct":14,"total":24,"identifiers":["__stripped__"]},"length":45,"vocabulary":21,"difficulty":6,"volume":197.65428402504423,"effort":1185.9257041502653,"bugs":0.0658847613416814,"time":65.88476134168141}}}],"maintainability":62.590740810161435,"module":"components/templates/templates.js"},"jshint":{"messages":[{"severity":"error","line":96,"column":25,"message":"'condition' is already defined.","source":"'{a}' is already defined."},{"severity":"error","line":130,"column":8,"message":"Missing semicolon.","source":"Missing semicolon."}]}}